cowinPy/__init__.py
cowinPy/cowinApis.py
cowinPY-0.1.0.dist-info/METADATA
cowinPY-0.1.0.dist-info/WHEEL
cowinPY-0.1.0.dist-info/top_level.txt
cowinPY-0.1.0.dist-info/RECORD
